MANIFEST.in
README.md
setup.py
cvlib/__init__.py
cvlib/face_detection.py
cvlib/gender_detection.py
cvlib/object_detection.py
cvlib/utils.py
cvlib.egg-info/PKG-INFO
cvlib.egg-info/SOURCES.txt
cvlib.egg-info/dependency_links.txt
cvlib.egg-info/not-zip-safe
cvlib.egg-info/requires.txt
cvlib.egg-info/top_level.txt
cvlib/data/deploy.prototxt
cvlib/data/res10_300x300_ssd_iter_140000.caffemodel