Metadata-Version: 1.0
Name: cvlib
Version: 0.2.1
Summary: A high level, easy to use, open source computer vision library for python
Home-page: https://github.com/arunponnusamy/cvlib.git
Author: Arun Ponnusamy
Author-email: hello@arunponnusamy.com
License: MIT
Platform: UNKNOWN
